[
    {
        "id": "4399063e84a0ab6e61735b791ca98cc835680267eaf71f8a40b758aa8e9104d2",
        "text": "Scraped from: scraped_data/tdx.vanderbilt.edu/tdx.vanderbilt.edu_part1.txt\nDate scraped: Unknown Date\n\nScraped from: https://tdx.vanderbilt.edu/TDClient/\nDate scraped: 2025-02-17 02:45:10\n\n\n================================================================================",
        "metadata": {
            "source": "scraped_data/tdx.vanderbilt.edu/tdx.vanderbilt.edu_part1.txt",
            "date_scraped": "Unknown Date",
            "chunk_number": 1
        }
    }
]