[
    {
        "id": "6eda2825-c425-4a93-b4f8-38ab8a6c7916",
        "text": "S",
        "metadata": {
            "page": 2,
            "source": "scraped_data/geo.vanderbilt.edu/geo.vanderbilt.edu_part1.txt"
        }
    },
    {
        "id": "5e967d4c-0345-4357-900c-f2a0ff75fc1a",
        "text": "c",
        "metadata": {
            "page": 3,
            "source": "scraped_data/geo.vanderbilt.edu/geo.vanderbilt.edu_part1.txt"
        }
    },
    {
        "id": "cd8dc1d9-0677-4b8b-b409-393f5770f0f9",
        "text": "r",
        "metadata": {
            "page": 4,
            "source": "scraped_data/geo.vanderbilt.edu/geo.vanderbilt.edu_part1.txt"
        }
    },
    {
        "id": "7b12e365-2cfe-4374-956e-68fa529162e2",
        "text": "a",
        "metadata": {
            "page": 5,
            "source": "scraped_data/geo.vanderbilt.edu/geo.vanderbilt.edu_part1.txt"
        }
    },
    {
        "id": "7799bb82-f730-4874-b80e-7db68f9ef7f7",
        "text": "p",
        "metadata": {
            "page": 6,
            "source": "scraped_data/geo.vanderbilt.edu/geo.vanderbilt.edu_part1.txt"
        }
    },
    {
        "id": "5f733722-ec68-4a3d-8714-cde76e34538e",
        "text": "e",
        "metadata": {
            "page": 7,
            "source": "scraped_data/geo.vanderbilt.edu/geo.vanderbilt.edu_part1.txt"
        }
    },
    {
        "id": "fedced92-ace0-48cb-bb3e-58e49f909169",
        "text": "d",
        "metadata": {
            "page": 8,
            "source": "scraped_data/geo.vanderbilt.edu/geo.vanderbilt.edu_part1.txt"
        }
    },
    {
        "id": "53da23fe-08b0-46d3-be4e-cb2365273376",
        "text": "f",
        "metadata": {
            "page": 10,
            "source": "scraped_data/geo.vanderbilt.edu/geo.vanderbilt.edu_part1.txt"
        }
    },
    {
        "id": "ee5c5566-14ac-4b65-af50-3878ced732ef",
        "text": "r",
        "metadata": {
            "page": 11,
            "source": "scraped_data/geo.vanderbilt.edu/geo.vanderbilt.edu_part1.txt"
        }
    },
    {
        "id": "cdb1fc2a-7ebb-4dab-b5f6-dc613bba6a44",
        "text": "o",
        "metadata": {
            "page": 12,
            "source": "scraped_data/geo.vanderbilt.edu/geo.vanderbilt.edu_part1.txt"
        }
    },
    {
        "id": "0f356c27-e860-4760-855f-f63853133db4",
        "text": "m",
        "metadata": {
            "page": 13,
            "source": "scraped_data/geo.vanderbilt.edu/geo.vanderbilt.edu_part1.txt"
        }
    },
    {
        "id": "16966dde-cbfa-4573-ad06-c6aa402d65c1",
        "text": ":",
        "metadata": {
            "page": 14,
            "source": "scraped_data/geo.vanderbilt.edu/geo.vanderbilt.edu_part1.txt"
        }
    },
    {
        "id": "57cf0592-b619-4567-9834-374d594c5ef6",
        "text": "h",
        "metadata": {
            "page": 16,
            "source": "scraped_data/geo.vanderbilt.edu/geo.vanderbilt.edu_part1.txt"
        }
    },
    {
        "id": "11dd6359-500a-499b-b934-9412033c6b37",
        "text": "t",
        "metadata": {
            "page": 17,
            "source": "scraped_data/geo.vanderbilt.edu/geo.vanderbilt.edu_part1.txt"
        }
    },
    {
        "id": "38eebae3-2d7f-4a96-a2a8-df41420d4fe4",
        "text": "t",
        "metadata": {
            "page": 18,
            "source": "scraped_data/geo.vanderbilt.edu/geo.vanderbilt.edu_part1.txt"
        }
    },
    {
        "id": "bdb465be-a38f-4814-957f-884e5bbfe576",
        "text": "p",
        "metadata": {
            "page": 19,
            "source": "scraped_data/geo.vanderbilt.edu/geo.vanderbilt.edu_part1.txt"
        }
    },
    {
        "id": "6573a338-aaaa-4eac-a589-a798e30491a9",
        "text": "s",
        "metadata": {
            "page": 20,
            "source": "scraped_data/geo.vanderbilt.edu/geo.vanderbilt.edu_part1.txt"
        }
    },
    {
        "id": "6f67e0e3-d4d6-49ce-8009-b311818390d2",
        "text": ":",
        "metadata": {
            "page": 21,
            "source": "scraped_data/geo.vanderbilt.edu/geo.vanderbilt.edu_part1.txt"
        }
    },
    {
        "id": "6a0f4965-6954-4204-b390-c2ae0e9aa26c",
        "text": "/",
        "metadata": {
            "page": 22,
            "source": "scraped_data/geo.vanderbilt.edu/geo.vanderbilt.edu_part1.txt"
        }
    },
    {
        "id": "e3fc73a4-6194-4f26-852a-57b7e40ed54d",
        "text": "/",
        "metadata": {
            "page": 23,
            "source": "scraped_data/geo.vanderbilt.edu/geo.vanderbilt.edu_part1.txt"
        }
    },
    {
        "id": "18af1ec3-edc1-4170-bbc8-59572037ee34",
        "text": "g",
        "metadata": {
            "page": 24,
            "source": "scraped_data/geo.vanderbilt.edu/geo.vanderbilt.edu_part1.txt"
        }
    },
    {
        "id": "fd6ca1d9-0ea2-4be0-b2d9-741f79777ff1",
        "text": "e",
        "metadata": {
            "page": 25,
            "source": "scraped_data/geo.vanderbilt.edu/geo.vanderbilt.edu_part1.txt"
        }
    },
    {
        "id": "d9b08af4-51e2-43a8-b56c-e11f4115a805",
        "text": "o",
        "metadata": {
            "page": 26,
            "source": "scraped_data/geo.vanderbilt.edu/geo.vanderbilt.edu_part1.txt"
        }
    },
    {
        "id": "90cc26b3-4958-45e1-84ec-da9e7c68db49",
        "text": ".",
        "metadata": {
            "page": 27,
            "source": "scraped_data/geo.vanderbilt.edu/geo.vanderbilt.edu_part1.txt"
        }
    },
    {
        "id": "e4baea7e-6204-4c34-a4e1-f4f826b41267",
        "text": "v",
        "metadata": {
            "page": 28,
            "source": "scraped_data/geo.vanderbilt.edu/geo.vanderbilt.edu_part1.txt"
        }
    },
    {
        "id": "bdd52e8d-9dda-4d64-a78d-d01d01138dfc",
        "text": "a",
        "metadata": {
            "page": 29,
            "source": "scraped_data/geo.vanderbilt.edu/geo.vanderbilt.edu_part1.txt"
        }
    },
    {
        "id": "ad1868c6-cbb8-4934-8e90-465ae5587495",
        "text": "n",
        "metadata": {
            "page": 30,
            "source": "scraped_data/geo.vanderbilt.edu/geo.vanderbilt.edu_part1.txt"
        }
    },
    {
        "id": "07014ef5-9bd7-4d7a-b411-caf5135d0618",
        "text": "d",
        "metadata": {
            "page": 31,
            "source": "scraped_data/geo.vanderbilt.edu/geo.vanderbilt.edu_part1.txt"
        }
    },
    {
        "id": "b89320a4-a5a1-4930-831a-0a21a1335dfd",
        "text": "e",
        "metadata": {
            "page": 32,
            "source": "scraped_data/geo.vanderbilt.edu/geo.vanderbilt.edu_part1.txt"
        }
    },
    {
        "id": "4c4b1d29-a492-4812-a9f4-74cf9bbdfa23",
        "text": "r",
        "metadata": {
            "page": 33,
            "source": "scraped_data/geo.vanderbilt.edu/geo.vanderbilt.edu_part1.txt"
        }
    },
    {
        "id": "cdb5a7fb-104b-4129-b454-0fd598e0cdc1",
        "text": "b",
        "metadata": {
            "page": 34,
            "source": "scraped_data/geo.vanderbilt.edu/geo.vanderbilt.edu_part1.txt"
        }
    },
    {
        "id": "343bfe08-3f5e-4372-997d-b3b90bf62051",
        "text": "i",
        "metadata": {
            "page": 35,
            "source": "scraped_data/geo.vanderbilt.edu/geo.vanderbilt.edu_part1.txt"
        }
    },
    {
        "id": "3f7d582f-7ce2-48b1-b920-8143c9b23d7e",
        "text": "l",
        "metadata": {
            "page": 36,
            "source": "scraped_data/geo.vanderbilt.edu/geo.vanderbilt.edu_part1.txt"
        }
    },
    {
        "id": "5c5d8d86-4278-48a1-865e-e386b45e97d6",
        "text": "t",
        "metadata": {
            "page": 37,
            "source": "scraped_data/geo.vanderbilt.edu/geo.vanderbilt.edu_part1.txt"
        }
    },
    {
        "id": "eb3ecfb2-5a10-4eb8-9677-111e6bc9473e",
        "text": ".",
        "metadata": {
            "page": 38,
            "source": "scraped_data/geo.vanderbilt.edu/geo.vanderbilt.edu_part1.txt"
        }
    },
    {
        "id": "6ab7f92f-c2df-49be-a6bd-a53a518cfea7",
        "text": "e",
        "metadata": {
            "page": 39,
            "source": "scraped_data/geo.vanderbilt.edu/geo.vanderbilt.edu_part1.txt"
        }
    },
    {
        "id": "b575a400-cef3-4039-80ed-04a4ad6883c9",
        "text": "d",
        "metadata": {
            "page": 40,
            "source": "scraped_data/geo.vanderbilt.edu/geo.vanderbilt.edu_part1.txt"
        }
    },
    {
        "id": "1d25d48d-709b-4ba8-af57-dff281bfb9ed",
        "text": "u",
        "metadata": {
            "page": 41,
            "source": "scraped_data/geo.vanderbilt.edu/geo.vanderbilt.edu_part1.txt"
        }
    },
    {
        "id": "1f97aa60-4127-45da-bb16-04ac01e8ae5e",
        "text": "/",
        "metadata": {
            "page": 42,
            "source": "scraped_data/geo.vanderbilt.edu/geo.vanderbilt.edu_part1.txt"
        }
    },
    {
        "id": "84eb15e6-72a5-4888-9c16-b8a6b80121d0",
        "text": "i",
        "metadata": {
            "page": 43,
            "source": "scraped_data/geo.vanderbilt.edu/geo.vanderbilt.edu_part1.txt"
        }
    },
    {
        "id": "75d38153-bb8b-496f-8fff-424802b3674a",
        "text": "n",
        "metadata": {
            "page": 44,
            "source": "scraped_data/geo.vanderbilt.edu/geo.vanderbilt.edu_part1.txt"
        }
    },
    {
        "id": "e528de3a-55d6-4d1e-8be4-6df4b9340d95",
        "text": "d",
        "metadata": {
            "page": 45,
            "source": "scraped_data/geo.vanderbilt.edu/geo.vanderbilt.edu_part1.txt"
        }
    },
    {
        "id": "aea2f214-f102-45da-852b-a6ff496a3218",
        "text": "e",
        "metadata": {
            "page": 46,
            "source": "scraped_data/geo.vanderbilt.edu/geo.vanderbilt.edu_part1.txt"
        }
    },
    {
        "id": "f84e898d-d6a4-4feb-bcf8-30023e1169d6",
        "text": "x",
        "metadata": {
            "page": 47,
            "source": "scraped_data/geo.vanderbilt.edu/geo.vanderbilt.edu_part1.txt"
        }
    },
    {
        "id": "31020a02-d439-4c75-9fd9-387a7011fac8",
        "text": ".",
        "metadata": {
            "page": 48,
            "source": "scraped_data/geo.vanderbilt.edu/geo.vanderbilt.edu_part1.txt"
        }
    },
    {
        "id": "4229b2b5-f076-417b-9216-046e4af20b08",
        "text": "c",
        "metadata": {
            "page": 49,
            "source": "scraped_data/geo.vanderbilt.edu/geo.vanderbilt.edu_part1.txt"
        }
    },
    {
        "id": "5225990b-21d6-42c0-97c7-a04400a2bfa6",
        "text": "f",
        "metadata": {
            "page": 50,
            "source": "scraped_data/geo.vanderbilt.edu/geo.vanderbilt.edu_part1.txt"
        }
    },
    {
        "id": "70758065-4e98-40d9-9eae-b08d0d2f3323",
        "text": "m",
        "metadata": {
            "page": 51,
            "source": "scraped_data/geo.vanderbilt.edu/geo.vanderbilt.edu_part1.txt"
        }
    },
    {
        "id": "a88bfd88-c53d-4cab-ba89-9bf15e1fa00d",
        "text": "/",
        "metadata": {
            "page": 52,
            "source": "scraped_data/geo.vanderbilt.edu/geo.vanderbilt.edu_part1.txt"
        }
    },
    {
        "id": "955695f2-7ab7-484f-9992-2971cc6869c2",
        "text": "D",
        "metadata": {
            "page": 54,
            "source": "scraped_data/geo.vanderbilt.edu/geo.vanderbilt.edu_part1.txt"
        }
    },
    {
        "id": "b440b86b-6cfd-4a80-8b6f-3f6675d026f4",
        "text": "a",
        "metadata": {
            "page": 55,
            "source": "scraped_data/geo.vanderbilt.edu/geo.vanderbilt.edu_part1.txt"
        }
    },
    {
        "id": "42c3955e-b7cf-4a27-820b-8aa477fbf165",
        "text": "t",
        "metadata": {
            "page": 56,
            "source": "scraped_data/geo.vanderbilt.edu/geo.vanderbilt.edu_part1.txt"
        }
    },
    {
        "id": "a56dd2ca-705e-4336-af15-b149e4e203a4",
        "text": "e",
        "metadata": {
            "page": 57,
            "source": "scraped_data/geo.vanderbilt.edu/geo.vanderbilt.edu_part1.txt"
        }
    },
    {
        "id": "dfc9b3b6-e188-4fd4-b3dd-e4fe3d34dd33",
        "text": "s",
        "metadata": {
            "page": 59,
            "source": "scraped_data/geo.vanderbilt.edu/geo.vanderbilt.edu_part1.txt"
        }
    },
    {
        "id": "0913bcf1-348b-42fa-a196-638fbd4314d8",
        "text": "c",
        "metadata": {
            "page": 60,
            "source": "scraped_data/geo.vanderbilt.edu/geo.vanderbilt.edu_part1.txt"
        }
    },
    {
        "id": "abced73b-04bd-4450-a293-f47f38bcbd38",
        "text": "r",
        "metadata": {
            "page": 61,
            "source": "scraped_data/geo.vanderbilt.edu/geo.vanderbilt.edu_part1.txt"
        }
    },
    {
        "id": "bfc35267-cb08-41a5-babd-271c65e5f5f1",
        "text": "a",
        "metadata": {
            "page": 62,
            "source": "scraped_data/geo.vanderbilt.edu/geo.vanderbilt.edu_part1.txt"
        }
    },
    {
        "id": "30114bb6-c475-4e55-940c-4c99ff37e7cb",
        "text": "p",
        "metadata": {
            "page": 63,
            "source": "scraped_data/geo.vanderbilt.edu/geo.vanderbilt.edu_part1.txt"
        }
    },
    {
        "id": "a991b716-4172-420b-843b-dccedc8ae197",
        "text": "e",
        "metadata": {
            "page": 64,
            "source": "scraped_data/geo.vanderbilt.edu/geo.vanderbilt.edu_part1.txt"
        }
    },
    {
        "id": "17bdbe0c-75dd-49e9-b14a-b0e75a99c207",
        "text": "d",
        "metadata": {
            "page": 65,
            "source": "scraped_data/geo.vanderbilt.edu/geo.vanderbilt.edu_part1.txt"
        }
    },
    {
        "id": "81292284-f60b-496d-9660-69f1fb0d068c",
        "text": ":",
        "metadata": {
            "page": 66,
            "source": "scraped_data/geo.vanderbilt.edu/geo.vanderbilt.edu_part1.txt"
        }
    },
    {
        "id": "09f9ec10-7149-4c9c-a4c7-230015e35cdc",
        "text": "2",
        "metadata": {
            "page": 68,
            "source": "scraped_data/geo.vanderbilt.edu/geo.vanderbilt.edu_part1.txt"
        }
    },
    {
        "id": "e8a0f0f2-9a3f-4a1e-98a4-9a383669fd39",
        "text": "0",
        "metadata": {
            "page": 69,
            "source": "scraped_data/geo.vanderbilt.edu/geo.vanderbilt.edu_part1.txt"
        }
    },
    {
        "id": "62fb36ad-918c-44c6-9e7a-b1624871fc0e",
        "text": "2",
        "metadata": {
            "page": 70,
            "source": "scraped_data/geo.vanderbilt.edu/geo.vanderbilt.edu_part1.txt"
        }
    },
    {
        "id": "e9c4f369-ee76-4571-8d8c-033a2c278f61",
        "text": "5",
        "metadata": {
            "page": 71,
            "source": "scraped_data/geo.vanderbilt.edu/geo.vanderbilt.edu_part1.txt"
        }
    },
    {
        "id": "69bace4f-40e0-41de-946c-bf833235622f",
        "text": "-",
        "metadata": {
            "page": 72,
            "source": "scraped_data/geo.vanderbilt.edu/geo.vanderbilt.edu_part1.txt"
        }
    },
    {
        "id": "799c9415-0983-46a4-998d-8f9beb174ceb",
        "text": "0",
        "metadata": {
            "page": 73,
            "source": "scraped_data/geo.vanderbilt.edu/geo.vanderbilt.edu_part1.txt"
        }
    },
    {
        "id": "408bf46b-35b7-4e87-a42e-4fb544825ba3",
        "text": "2",
        "metadata": {
            "page": 74,
            "source": "scraped_data/geo.vanderbilt.edu/geo.vanderbilt.edu_part1.txt"
        }
    },
    {
        "id": "d4cd0e69-c9b3-46f2-9ad1-036ef75431ad",
        "text": "-",
        "metadata": {
            "page": 75,
            "source": "scraped_data/geo.vanderbilt.edu/geo.vanderbilt.edu_part1.txt"
        }
    },
    {
        "id": "aaa15563-ea26-4529-9256-acf6ae599b6b",
        "text": "1",
        "metadata": {
            "page": 76,
            "source": "scraped_data/geo.vanderbilt.edu/geo.vanderbilt.edu_part1.txt"
        }
    },
    {
        "id": "91f3af8d-cff4-4817-8691-3005fca92651",
        "text": "7",
        "metadata": {
            "page": 77,
            "source": "scraped_data/geo.vanderbilt.edu/geo.vanderbilt.edu_part1.txt"
        }
    },
    {
        "id": "23b943ce-c573-415e-b8d3-80c90aac83ac",
        "text": "0",
        "metadata": {
            "page": 79,
            "source": "scraped_data/geo.vanderbilt.edu/geo.vanderbilt.edu_part1.txt"
        }
    },
    {
        "id": "760fde0f-52a0-452d-af3d-cbe4d2af13f6",
        "text": "2",
        "metadata": {
            "page": 80,
            "source": "scraped_data/geo.vanderbilt.edu/geo.vanderbilt.edu_part1.txt"
        }
    },
    {
        "id": "2dac3259-f072-44ce-a6bc-c983854b8527",
        "text": ":",
        "metadata": {
            "page": 81,
            "source": "scraped_data/geo.vanderbilt.edu/geo.vanderbilt.edu_part1.txt"
        }
    },
    {
        "id": "72fca577-c8a9-4f40-afe2-8419a4766ffb",
        "text": "4",
        "metadata": {
            "page": 82,
            "source": "scraped_data/geo.vanderbilt.edu/geo.vanderbilt.edu_part1.txt"
        }
    },
    {
        "id": "67ac7280-3af0-4d4d-9bdb-9b79a443cdd7",
        "text": "5",
        "metadata": {
            "page": 83,
            "source": "scraped_data/geo.vanderbilt.edu/geo.vanderbilt.edu_part1.txt"
        }
    },
    {
        "id": "eb21a44e-7cae-45aa-b219-074c298b1341",
        "text": ":",
        "metadata": {
            "page": 84,
            "source": "scraped_data/geo.vanderbilt.edu/geo.vanderbilt.edu_part1.txt"
        }
    },
    {
        "id": "62136f05-0375-4f61-a67f-2767561f2e72",
        "text": "1",
        "metadata": {
            "page": 85,
            "source": "scraped_data/geo.vanderbilt.edu/geo.vanderbilt.edu_part1.txt"
        }
    },
    {
        "id": "352a0c23-043d-42de-afb6-e0e92cc7bfd1",
        "text": "0",
        "metadata": {
            "page": 86,
            "source": "scraped_data/geo.vanderbilt.edu/geo.vanderbilt.edu_part1.txt"
        }
    },
    {
        "id": "7780baeb-d0ec-419d-9db3-f74095ae89fe",
        "text": "Y",
        "metadata": {
            "page": 89,
            "source": "scraped_data/geo.vanderbilt.edu/geo.vanderbilt.edu_part1.txt"
        }
    },
    {
        "id": "df524be1-26b9-434e-a36a-6fbe736ba4d4",
        "text": "o",
        "metadata": {
            "page": 90,
            "source": "scraped_data/geo.vanderbilt.edu/geo.vanderbilt.edu_part1.txt"
        }
    },
    {
        "id": "d2d72bd6-c162-46a0-9f75-d3d9975b5966",
        "text": "u",
        "metadata": {
            "page": 91,
            "source": "scraped_data/geo.vanderbilt.edu/geo.vanderbilt.edu_part1.txt"
        }
    },
    {
        "id": "a82981c2-0859-4567-99f6-1096949cbbf6",
        "text": "r",
        "metadata": {
            "page": 92,
            "source": "scraped_data/geo.vanderbilt.edu/geo.vanderbilt.edu_part1.txt"
        }
    },
    {
        "id": "5644994c-4cd7-42f1-8237-0d0a637a1e29",
        "text": "b",
        "metadata": {
            "page": 94,
            "source": "scraped_data/geo.vanderbilt.edu/geo.vanderbilt.edu_part1.txt"
        }
    },
    {
        "id": "210f310c-6115-4828-b804-4b2853a9c28c",
        "text": "r",
        "metadata": {
            "page": 95,
            "source": "scraped_data/geo.vanderbilt.edu/geo.vanderbilt.edu_part1.txt"
        }
    },
    {
        "id": "58425998-1941-4b30-aa86-e38fe82554e9",
        "text": "o",
        "metadata": {
            "page": 96,
            "source": "scraped_data/geo.vanderbilt.edu/geo.vanderbilt.edu_part1.txt"
        }
    },
    {
        "id": "5d402611-4f30-4fcc-8c98-b7788fc775dd",
        "text": "w",
        "metadata": {
            "page": 97,
            "source": "scraped_data/geo.vanderbilt.edu/geo.vanderbilt.edu_part1.txt"
        }
    },
    {
        "id": "88262ab1-62a1-4892-9b4e-b63958bc29be",
        "text": "s",
        "metadata": {
            "page": 98,
            "source": "scraped_data/geo.vanderbilt.edu/geo.vanderbilt.edu_part1.txt"
        }
    },
    {
        "id": "a3e901d7-a3c4-4126-91c5-c73226c2a692",
        "text": "e",
        "metadata": {
            "page": 99,
            "source": "scraped_data/geo.vanderbilt.edu/geo.vanderbilt.edu_part1.txt"
        }
    },
    {
        "id": "8efd43dc-ed6f-47d6-a807-5e2d8b218ef6",
        "text": "r",
        "metadata": {
            "page": 100,
            "source": "scraped_data/geo.vanderbilt.edu/geo.vanderbilt.edu_part1.txt"
        }
    },
    {
        "id": "4ca7df3a-3df3-4b32-8bc6-64b471f7aaf8",
        "text": "d",
        "metadata": {
            "page": 102,
            "source": "scraped_data/geo.vanderbilt.edu/geo.vanderbilt.edu_part1.txt"
        }
    },
    {
        "id": "f7486621-9179-4b19-9eb0-875a46660cc8",
        "text": "o",
        "metadata": {
            "page": 103,
            "source": "scraped_data/geo.vanderbilt.edu/geo.vanderbilt.edu_part1.txt"
        }
    },
    {
        "id": "8b10d0ef-fda5-4969-a635-e615fd4a6148",
        "text": "e",
        "metadata": {
            "page": 104,
            "source": "scraped_data/geo.vanderbilt.edu/geo.vanderbilt.edu_part1.txt"
        }
    },
    {
        "id": "2a73da64-672b-4197-8a42-ed360fda31e6",
        "text": "s",
        "metadata": {
            "page": 105,
            "source": "scraped_data/geo.vanderbilt.edu/geo.vanderbilt.edu_part1.txt"
        }
    },
    {
        "id": "59ba0b79-f637-4eea-9c1f-12dc20c84de7",
        "text": "n",
        "metadata": {
            "page": 107,
            "source": "scraped_data/geo.vanderbilt.edu/geo.vanderbilt.edu_part1.txt"
        }
    },
    {
        "id": "5017ca8b-a9d4-429c-b6d7-4924dc45ad7d",
        "text": "o",
        "metadata": {
            "page": 108,
            "source": "scraped_data/geo.vanderbilt.edu/geo.vanderbilt.edu_part1.txt"
        }
    },
    {
        "id": "e00fba37-7fd4-46d7-9ae8-75d0383cba7a",
        "text": "t",
        "metadata": {
            "page": 109,
            "source": "scraped_data/geo.vanderbilt.edu/geo.vanderbilt.edu_part1.txt"
        }
    },
    {
        "id": "a1f00379-5ae3-4ec9-b391-819c91e50af3",
        "text": "s",
        "metadata": {
            "page": 111,
            "source": "scraped_data/geo.vanderbilt.edu/geo.vanderbilt.edu_part1.txt"
        }
    },
    {
        "id": "1293c0f7-6c08-407a-86cb-085edf8a2f8f",
        "text": "u",
        "metadata": {
            "page": 112,
            "source": "scraped_data/geo.vanderbilt.edu/geo.vanderbilt.edu_part1.txt"
        }
    },
    {
        "id": "57866c6a-80b8-4aa0-8b55-94699181e5bc",
        "text": "p",
        "metadata": {
            "page": 113,
            "source": "scraped_data/geo.vanderbilt.edu/geo.vanderbilt.edu_part1.txt"
        }
    },
    {
        "id": "43bca975-d08c-4ea0-b6e0-fd15b0f4f0a7",
        "text": "p",
        "metadata": {
            "page": 114,
            "source": "scraped_data/geo.vanderbilt.edu/geo.vanderbilt.edu_part1.txt"
        }
    },
    {
        "id": "c092d437-d857-40c0-a523-1745c1af2fff",
        "text": "o",
        "metadata": {
            "page": 115,
            "source": "scraped_data/geo.vanderbilt.edu/geo.vanderbilt.edu_part1.txt"
        }
    },
    {
        "id": "ae79450d-ef8d-4168-9710-bb12ced8f9ae",
        "text": "r",
        "metadata": {
            "page": 116,
            "source": "scraped_data/geo.vanderbilt.edu/geo.vanderbilt.edu_part1.txt"
        }
    },
    {
        "id": "372c81d1-6841-440a-899c-31f2294c1bb5",
        "text": "t",
        "metadata": {
            "page": 117,
            "source": "scraped_data/geo.vanderbilt.edu/geo.vanderbilt.edu_part1.txt"
        }
    },
    {
        "id": "c795c6c7-fa81-40c4-90d9-208fcb40f52f",
        "text": "J",
        "metadata": {
            "page": 119,
            "source": "scraped_data/geo.vanderbilt.edu/geo.vanderbilt.edu_part1.txt"
        }
    },
    {
        "id": "7e01f514-0ab8-4ae1-b205-ab33f1448690",
        "text": "a",
        "metadata": {
            "page": 120,
            "source": "scraped_data/geo.vanderbilt.edu/geo.vanderbilt.edu_part1.txt"
        }
    },
    {
        "id": "fb41e7da-c3fc-4ac4-812f-04589eef422d",
        "text": "v",
        "metadata": {
            "page": 121,
            "source": "scraped_data/geo.vanderbilt.edu/geo.vanderbilt.edu_part1.txt"
        }
    },
    {
        "id": "da568bf0-15da-44c0-ac3e-c66c1439702d",
        "text": "a",
        "metadata": {
            "page": 122,
            "source": "scraped_data/geo.vanderbilt.edu/geo.vanderbilt.edu_part1.txt"
        }
    },
    {
        "id": "f00925ad-adc4-48ca-8ab4-0e72a66b4869",
        "text": "S",
        "metadata": {
            "page": 123,
            "source": "scraped_data/geo.vanderbilt.edu/geo.vanderbilt.edu_part1.txt"
        }
    },
    {
        "id": "78f6f8fe-2268-435a-9958-31f06109fece",
        "text": "c",
        "metadata": {
            "page": 124,
            "source": "scraped_data/geo.vanderbilt.edu/geo.vanderbilt.edu_part1.txt"
        }
    },
    {
        "id": "12f9d5d3-4c06-4b05-9876-cde1efa79666",
        "text": "r",
        "metadata": {
            "page": 125,
            "source": "scraped_data/geo.vanderbilt.edu/geo.vanderbilt.edu_part1.txt"
        }
    },
    {
        "id": "644507dd-e34d-4ff2-8ce1-bb4b0d627e19",
        "text": "i",
        "metadata": {
            "page": 126,
            "source": "scraped_data/geo.vanderbilt.edu/geo.vanderbilt.edu_part1.txt"
        }
    },
    {
        "id": "b59142c7-c394-46d5-be7c-32b0589f10c5",
        "text": "p",
        "metadata": {
            "page": 127,
            "source": "scraped_data/geo.vanderbilt.edu/geo.vanderbilt.edu_part1.txt"
        }
    },
    {
        "id": "45386380-d672-4274-83c0-bf0ce22b0cff",
        "text": "t",
        "metadata": {
            "page": 128,
            "source": "scraped_data/geo.vanderbilt.edu/geo.vanderbilt.edu_part1.txt"
        }
    },
    {
        "id": "969fcdf6-a6b7-4d48-86d6-637e6518923f",
        "text": ",",
        "metadata": {
            "page": 129,
            "source": "scraped_data/geo.vanderbilt.edu/geo.vanderbilt.edu_part1.txt"
        }
    },
    {
        "id": "6cb39570-d2dd-45fb-b2c7-41e8ea322301",
        "text": "o",
        "metadata": {
            "page": 131,
            "source": "scraped_data/geo.vanderbilt.edu/geo.vanderbilt.edu_part1.txt"
        }
    },
    {
        "id": "5c7a4cbd-57fe-4f52-b5ce-01e205090edb",
        "text": "r",
        "metadata": {
            "page": 132,
            "source": "scraped_data/geo.vanderbilt.edu/geo.vanderbilt.edu_part1.txt"
        }
    },
    {
        "id": "7dc5a874-8410-48a4-84dc-c24823063e08",
        "text": "i",
        "metadata": {
            "page": 134,
            "source": "scraped_data/geo.vanderbilt.edu/geo.vanderbilt.edu_part1.txt"
        }
    },
    {
        "id": "95c4a1a0-f07a-4676-9ac3-a1b2cc5ad89b",
        "text": "t",
        "metadata": {
            "page": 135,
            "source": "scraped_data/geo.vanderbilt.edu/geo.vanderbilt.edu_part1.txt"
        }
    },
    {
        "id": "8ab23bd8-66fb-4bf8-9727-4765a8e957fd",
        "text": "i",
        "metadata": {
            "page": 137,
            "source": "scraped_data/geo.vanderbilt.edu/geo.vanderbilt.edu_part1.txt"
        }
    },
    {
        "id": "6512447b-34b8-4002-a17f-22b6161ffed2",
        "text": "s",
        "metadata": {
            "page": 138,
            "source": "scraped_data/geo.vanderbilt.edu/geo.vanderbilt.edu_part1.txt"
        }
    },
    {
        "id": "0e55afb9-6503-4d0d-9bb3-6ca7282de26a",
        "text": "c",
        "metadata": {
            "page": 140,
            "source": "scraped_data/geo.vanderbilt.edu/geo.vanderbilt.edu_part1.txt"
        }
    },
    {
        "id": "a3b5ea48-bb73-4966-befe-f4b5a1dbb7b8",
        "text": "u",
        "metadata": {
            "page": 141,
            "source": "scraped_data/geo.vanderbilt.edu/geo.vanderbilt.edu_part1.txt"
        }
    },
    {
        "id": "c6dc5887-14bf-476d-865a-4d7f45853a81",
        "text": "r",
        "metadata": {
            "page": 142,
            "source": "scraped_data/geo.vanderbilt.edu/geo.vanderbilt.edu_part1.txt"
        }
    },
    {
        "id": "2d63a4ab-4dcd-41cd-9ca1-9eccf1283162",
        "text": "r",
        "metadata": {
            "page": 143,
            "source": "scraped_data/geo.vanderbilt.edu/geo.vanderbilt.edu_part1.txt"
        }
    },
    {
        "id": "91553476-270e-49fd-9dbf-f80de1b0e0b2",
        "text": "e",
        "metadata": {
            "page": 144,
            "source": "scraped_data/geo.vanderbilt.edu/geo.vanderbilt.edu_part1.txt"
        }
    },
    {
        "id": "eae65956-6314-4942-9e61-d12709ca5e26",
        "text": "n",
        "metadata": {
            "page": 145,
            "source": "scraped_data/geo.vanderbilt.edu/geo.vanderbilt.edu_part1.txt"
        }
    },
    {
        "id": "9874d345-d80a-4285-8e0d-2df041361b50",
        "text": "t",
        "metadata": {
            "page": 146,
            "source": "scraped_data/geo.vanderbilt.edu/geo.vanderbilt.edu_part1.txt"
        }
    },
    {
        "id": "a2687914-18b3-40c6-abf3-098f17e5800b",
        "text": "l",
        "metadata": {
            "page": 147,
            "source": "scraped_data/geo.vanderbilt.edu/geo.vanderbilt.edu_part1.txt"
        }
    },
    {
        "id": "fe8bfd6d-7818-4a14-bb50-2b2e0efca0b6",
        "text": "y",
        "metadata": {
            "page": 148,
            "source": "scraped_data/geo.vanderbilt.edu/geo.vanderbilt.edu_part1.txt"
        }
    },
    {
        "id": "db43603c-9910-4314-b82f-a6fd98a5045e",
        "text": "d",
        "metadata": {
            "page": 150,
            "source": "scraped_data/geo.vanderbilt.edu/geo.vanderbilt.edu_part1.txt"
        }
    },
    {
        "id": "4db28541-c13c-483f-9cdb-b2fc4e19441e",
        "text": "i",
        "metadata": {
            "page": 151,
            "source": "scraped_data/geo.vanderbilt.edu/geo.vanderbilt.edu_part1.txt"
        }
    },
    {
        "id": "3b464a0e-8477-4979-a5c7-0e704c7b12ec",
        "text": "s",
        "metadata": {
            "page": 152,
            "source": "scraped_data/geo.vanderbilt.edu/geo.vanderbilt.edu_part1.txt"
        }
    },
    {
        "id": "3c56d7af-3d0e-4d37-92f6-5d2c3d83914e",
        "text": "a",
        "metadata": {
            "page": 153,
            "source": "scraped_data/geo.vanderbilt.edu/geo.vanderbilt.edu_part1.txt"
        }
    },
    {
        "id": "1da03bfe-8eb9-4459-99ae-2711aece144e",
        "text": "b",
        "metadata": {
            "page": 154,
            "source": "scraped_data/geo.vanderbilt.edu/geo.vanderbilt.edu_part1.txt"
        }
    },
    {
        "id": "37777338-d76d-4738-8f29-bab2a9d117b6",
        "text": "l",
        "metadata": {
            "page": 155,
            "source": "scraped_data/geo.vanderbilt.edu/geo.vanderbilt.edu_part1.txt"
        }
    },
    {
        "id": "a9618760-ed37-4bd8-a0d7-accff69acb8e",
        "text": "e",
        "metadata": {
            "page": 156,
            "source": "scraped_data/geo.vanderbilt.edu/geo.vanderbilt.edu_part1.txt"
        }
    },
    {
        "id": "337157de-271c-47bb-b335-3a89369f6291",
        "text": "d",
        "metadata": {
            "page": 157,
            "source": "scraped_data/geo.vanderbilt.edu/geo.vanderbilt.edu_part1.txt"
        }
    },
    {
        "id": "0569044b-56fe-4c22-8226-3338b41820f0",
        "text": ".",
        "metadata": {
            "page": 158,
            "source": "scraped_data/geo.vanderbilt.edu/geo.vanderbilt.edu_part1.txt"
        }
    },
    {
        "id": "a07f65d6-c33c-4691-a7f6-800b5d178637",
        "text": "T",
        "metadata": {
            "page": 160,
            "source": "scraped_data/geo.vanderbilt.edu/geo.vanderbilt.edu_part1.txt"
        }
    },
    {
        "id": "8712620c-c44d-4de5-885c-a0e3b5439f8d",
        "text": "h",
        "metadata": {
            "page": 161,
            "source": "scraped_data/geo.vanderbilt.edu/geo.vanderbilt.edu_part1.txt"
        }
    },
    {
        "id": "79bea8bb-411a-4904-a0d5-c7047ee5ffcb",
        "text": "i",
        "metadata": {
            "page": 162,
            "source": "scraped_data/geo.vanderbilt.edu/geo.vanderbilt.edu_part1.txt"
        }
    },
    {
        "id": "5a3c4da7-0669-4e17-b597-d2f204bf0b96",
        "text": "s",
        "metadata": {
            "page": 163,
            "source": "scraped_data/geo.vanderbilt.edu/geo.vanderbilt.edu_part1.txt"
        }
    },
    {
        "id": "b9819fa1-3a85-4871-ae30-5760da92c58b",
        "text": "s",
        "metadata": {
            "page": 165,
            "source": "scraped_data/geo.vanderbilt.edu/geo.vanderbilt.edu_part1.txt"
        }
    },
    {
        "id": "7896ccac-053a-4e57-8c62-01a9ba8054d1",
        "text": "i",
        "metadata": {
            "page": 166,
            "source": "scraped_data/geo.vanderbilt.edu/geo.vanderbilt.edu_part1.txt"
        }
    },
    {
        "id": "102e97e2-e54a-44f2-9358-0579b437c0a9",
        "text": "t",
        "metadata": {
            "page": 167,
            "source": "scraped_data/geo.vanderbilt.edu/geo.vanderbilt.edu_part1.txt"
        }
    },
    {
        "id": "4c85b0c3-2a0a-42bd-9fc4-78bdb7313f8b",
        "text": "e",
        "metadata": {
            "page": 168,
            "source": "scraped_data/geo.vanderbilt.edu/geo.vanderbilt.edu_part1.txt"
        }
    },
    {
        "id": "5ff679c5-f27b-4e46-ae0c-7e924a802696",
        "text": "r",
        "metadata": {
            "page": 170,
            "source": "scraped_data/geo.vanderbilt.edu/geo.vanderbilt.edu_part1.txt"
        }
    },
    {
        "id": "6110bc73-266f-4f46-853e-80ae8b4a3061",
        "text": "e",
        "metadata": {
            "page": 171,
            "source": "scraped_data/geo.vanderbilt.edu/geo.vanderbilt.edu_part1.txt"
        }
    },
    {
        "id": "306f6c66-edf8-4df7-8d6a-f6cefc1a834c",
        "text": "q",
        "metadata": {
            "page": 172,
            "source": "scraped_data/geo.vanderbilt.edu/geo.vanderbilt.edu_part1.txt"
        }
    },
    {
        "id": "5bce34c7-0301-4cc9-a5c7-c727b6827ab0",
        "text": "u",
        "metadata": {
            "page": 173,
            "source": "scraped_data/geo.vanderbilt.edu/geo.vanderbilt.edu_part1.txt"
        }
    },
    {
        "id": "c8933894-4e82-47ce-b6df-e70ef1fb55a5",
        "text": "i",
        "metadata": {
            "page": 174,
            "source": "scraped_data/geo.vanderbilt.edu/geo.vanderbilt.edu_part1.txt"
        }
    },
    {
        "id": "cc7ecf1e-e6d5-4fb6-859d-c7915559601d",
        "text": "r",
        "metadata": {
            "page": 175,
            "source": "scraped_data/geo.vanderbilt.edu/geo.vanderbilt.edu_part1.txt"
        }
    },
    {
        "id": "e9b27033-86a3-4255-9b71-40e54acc49d1",
        "text": "e",
        "metadata": {
            "page": 176,
            "source": "scraped_data/geo.vanderbilt.edu/geo.vanderbilt.edu_part1.txt"
        }
    },
    {
        "id": "4baca189-012a-4cb7-a465-50ade96f626c",
        "text": "s",
        "metadata": {
            "page": 177,
            "source": "scraped_data/geo.vanderbilt.edu/geo.vanderbilt.edu_part1.txt"
        }
    },
    {
        "id": "dff6e197-b744-4aef-a544-4b5f7b3cf838",
        "text": "J",
        "metadata": {
            "page": 179,
            "source": "scraped_data/geo.vanderbilt.edu/geo.vanderbilt.edu_part1.txt"
        }
    },
    {
        "id": "7054403e-e84c-4cea-91b1-eb4ed7a38f10",
        "text": "a",
        "metadata": {
            "page": 180,
            "source": "scraped_data/geo.vanderbilt.edu/geo.vanderbilt.edu_part1.txt"
        }
    },
    {
        "id": "811f91da-40c8-48cd-b113-6db382d6c460",
        "text": "v",
        "metadata": {
            "page": 181,
            "source": "scraped_data/geo.vanderbilt.edu/geo.vanderbilt.edu_part1.txt"
        }
    },
    {
        "id": "f4fa4094-67f1-4ccc-ab58-a2d8f5188d10",
        "text": "a",
        "metadata": {
            "page": 182,
            "source": "scraped_data/geo.vanderbilt.edu/geo.vanderbilt.edu_part1.txt"
        }
    },
    {
        "id": "0fe802f6-1535-4c40-ac04-7986050de53a",
        "text": "S",
        "metadata": {
            "page": 183,
            "source": "scraped_data/geo.vanderbilt.edu/geo.vanderbilt.edu_part1.txt"
        }
    },
    {
        "id": "3d2fc11f-f0c9-4b4f-be42-c282c98b7fed",
        "text": "c",
        "metadata": {
            "page": 184,
            "source": "scraped_data/geo.vanderbilt.edu/geo.vanderbilt.edu_part1.txt"
        }
    },
    {
        "id": "f80f2831-950d-4f75-976b-36d92d1d1572",
        "text": "r",
        "metadata": {
            "page": 185,
            "source": "scraped_data/geo.vanderbilt.edu/geo.vanderbilt.edu_part1.txt"
        }
    },
    {
        "id": "e4cab24e-5c3f-4de1-b092-1ff1f031ff3e",
        "text": "i",
        "metadata": {
            "page": 186,
            "source": "scraped_data/geo.vanderbilt.edu/geo.vanderbilt.edu_part1.txt"
        }
    },
    {
        "id": "240e2222-627c-489e-bf4d-18d0458871b1",
        "text": "p",
        "metadata": {
            "page": 187,
            "source": "scraped_data/geo.vanderbilt.edu/geo.vanderbilt.edu_part1.txt"
        }
    },
    {
        "id": "5b15a7ff-2837-43f7-a466-e989525f7ab6",
        "text": "t",
        "metadata": {
            "page": 188,
            "source": "scraped_data/geo.vanderbilt.edu/geo.vanderbilt.edu_part1.txt"
        }
    },
    {
        "id": "94595e07-f777-42da-8c3d-37901c1e54b5",
        "text": "s",
        "metadata": {
            "page": 190,
            "source": "scraped_data/geo.vanderbilt.edu/geo.vanderbilt.edu_part1.txt"
        }
    },
    {
        "id": "9ad9d36c-e04d-49e5-9669-eea958e5de06",
        "text": "u",
        "metadata": {
            "page": 191,
            "source": "scraped_data/geo.vanderbilt.edu/geo.vanderbilt.edu_part1.txt"
        }
    },
    {
        "id": "3bcd62c1-1754-44b5-a75a-8498dfb9d48f",
        "text": "p",
        "metadata": {
            "page": 192,
            "source": "scraped_data/geo.vanderbilt.edu/geo.vanderbilt.edu_part1.txt"
        }
    },
    {
        "id": "b58cb0a0-8518-45ad-9a02-9959c06d2bb3",
        "text": "p",
        "metadata": {
            "page": 193,
            "source": "scraped_data/geo.vanderbilt.edu/geo.vanderbilt.edu_part1.txt"
        }
    },
    {
        "id": "8eaac654-73f4-4545-882b-e0e215283c08",
        "text": "o",
        "metadata": {
            "page": 194,
            "source": "scraped_data/geo.vanderbilt.edu/geo.vanderbilt.edu_part1.txt"
        }
    },
    {
        "id": "ddac19a6-670c-4f09-9243-07ec4f19f05a",
        "text": "r",
        "metadata": {
            "page": 195,
            "source": "scraped_data/geo.vanderbilt.edu/geo.vanderbilt.edu_part1.txt"
        }
    },
    {
        "id": "ca81aa9f-71e8-4735-99e6-a540baade846",
        "text": "t",
        "metadata": {
            "page": 196,
            "source": "scraped_data/geo.vanderbilt.edu/geo.vanderbilt.edu_part1.txt"
        }
    },
    {
        "id": "591d3a12-d903-4394-a301-a107848b5d08",
        "text": "t",
        "metadata": {
            "page": 198,
            "source": "scraped_data/geo.vanderbilt.edu/geo.vanderbilt.edu_part1.txt"
        }
    },
    {
        "id": "cc087e3c-d914-4bc7-99d6-77ebe816acd8",
        "text": "o",
        "metadata": {
            "page": 199,
            "source": "scraped_data/geo.vanderbilt.edu/geo.vanderbilt.edu_part1.txt"
        }
    },
    {
        "id": "f4223849-9ba0-499c-b966-bbdd6a4a842c",
        "text": "r",
        "metadata": {
            "page": 201,
            "source": "scraped_data/geo.vanderbilt.edu/geo.vanderbilt.edu_part1.txt"
        }
    },
    {
        "id": "5f5abf6a-ca60-4db2-81ba-9d73febd2f1d",
        "text": "u",
        "metadata": {
            "page": 202,
            "source": "scraped_data/geo.vanderbilt.edu/geo.vanderbilt.edu_part1.txt"
        }
    },
    {
        "id": "02e9fae1-6787-4bdd-a8f5-72d03e9c8126",
        "text": "n",
        "metadata": {
            "page": 203,
            "source": "scraped_data/geo.vanderbilt.edu/geo.vanderbilt.edu_part1.txt"
        }
    },
    {
        "id": "5ae3368f-f23a-4ecd-a6e2-5e1268de723a",
        "text": "p",
        "metadata": {
            "page": 205,
            "source": "scraped_data/geo.vanderbilt.edu/geo.vanderbilt.edu_part1.txt"
        }
    },
    {
        "id": "102c2e63-556b-4932-828f-85a4741b575b",
        "text": "r",
        "metadata": {
            "page": 206,
            "source": "scraped_data/geo.vanderbilt.edu/geo.vanderbilt.edu_part1.txt"
        }
    },
    {
        "id": "6b7c3fe7-8921-4477-a0cf-74a95c331189",
        "text": "o",
        "metadata": {
            "page": 207,
            "source": "scraped_data/geo.vanderbilt.edu/geo.vanderbilt.edu_part1.txt"
        }
    },
    {
        "id": "a87f4f34-40b4-4cb7-9cb2-d49dfc024b1a",
        "text": "p",
        "metadata": {
            "page": 208,
            "source": "scraped_data/geo.vanderbilt.edu/geo.vanderbilt.edu_part1.txt"
        }
    },
    {
        "id": "d45e046e-a17c-4d59-ae2f-78e598d3b6c1",
        "text": "e",
        "metadata": {
            "page": 209,
            "source": "scraped_data/geo.vanderbilt.edu/geo.vanderbilt.edu_part1.txt"
        }
    },
    {
        "id": "c0f3bc44-05a4-4ff6-9993-6f84ce8d5bea",
        "text": "r",
        "metadata": {
            "page": 210,
            "source": "scraped_data/geo.vanderbilt.edu/geo.vanderbilt.edu_part1.txt"
        }
    },
    {
        "id": "4b603591-d864-4f05-9281-7d6a3b073b50",
        "text": "l",
        "metadata": {
            "page": 211,
            "source": "scraped_data/geo.vanderbilt.edu/geo.vanderbilt.edu_part1.txt"
        }
    },
    {
        "id": "f8394034-2252-4dd2-9dc6-29f5a2fbceca",
        "text": "y",
        "metadata": {
            "page": 212,
            "source": "scraped_data/geo.vanderbilt.edu/geo.vanderbilt.edu_part1.txt"
        }
    },
    {
        "id": "15603f62-947f-436d-a06e-a4ce8410ea28",
        "text": ".",
        "metadata": {
            "page": 213,
            "source": "scraped_data/geo.vanderbilt.edu/geo.vanderbilt.edu_part1.txt"
        }
    },
    {
        "id": "78ef1002-0d29-4c08-90b9-95be2a231952",
        "text": "=",
        "metadata": {
            "page": 217,
            "source": "scraped_data/geo.vanderbilt.edu/geo.vanderbilt.edu_part1.txt"
        }
    },
    {
        "id": "6cb4420a-2b9d-40e0-8437-0b969120dfda",
        "text": "=",
        "metadata": {
            "page": 218,
            "source": "scraped_data/geo.vanderbilt.edu/geo.vanderbilt.edu_part1.txt"
        }
    },
    {
        "id": "e6d51804-5a1b-4c7d-b6eb-519c7a3c9c9a",
        "text": "=",
        "metadata": {
            "page": 219,
            "source": "scraped_data/geo.vanderbilt.edu/geo.vanderbilt.edu_part1.txt"
        }
    },
    {
        "id": "ec37faf8-1038-4357-88ad-7b99369cad5e",
        "text": "=",
        "metadata": {
            "page": 220,
            "source": "scraped_data/geo.vanderbilt.edu/geo.vanderbilt.edu_part1.txt"
        }
    },
    {
        "id": "ef8c7902-6da8-4df2-aae7-8320f0d4ee92",
        "text": "=",
        "metadata": {
            "page": 221,
            "source": "scraped_data/geo.vanderbilt.edu/geo.vanderbilt.edu_part1.txt"
        }
    },
    {
        "id": "d8b85ce1-6c39-45e2-8174-a606398fc633",
        "text": "=",
        "metadata": {
            "page": 222,
            "source": "scraped_data/geo.vanderbilt.edu/geo.vanderbilt.edu_part1.txt"
        }
    },
    {
        "id": "ca10b538-bfa9-4b9a-973d-78d8f40ee2d5",
        "text": "=",
        "metadata": {
            "page": 223,
            "source": "scraped_data/geo.vanderbilt.edu/geo.vanderbilt.edu_part1.txt"
        }
    },
    {
        "id": "3e0a5289-aa79-4c30-8191-13eba52e7e6f",
        "text": "=",
        "metadata": {
            "page": 224,
            "source": "scraped_data/geo.vanderbilt.edu/geo.vanderbilt.edu_part1.txt"
        }
    },
    {
        "id": "bdd539f9-355a-4f29-a3db-e05d8595273b",
        "text": "=",
        "metadata": {
            "page": 225,
            "source": "scraped_data/geo.vanderbilt.edu/geo.vanderbilt.edu_part1.txt"
        }
    },
    {
        "id": "2e00b8eb-7947-4027-a423-1bfb015a7c11",
        "text": "=",
        "metadata": {
            "page": 226,
            "source": "scraped_data/geo.vanderbilt.edu/geo.vanderbilt.edu_part1.txt"
        }
    },
    {
        "id": "64e46e7f-5a83-40e9-b9b3-91e030e42762",
        "text": "=",
        "metadata": {
            "page": 227,
            "source": "scraped_data/geo.vanderbilt.edu/geo.vanderbilt.edu_part1.txt"
        }
    },
    {
        "id": "e1dd0216-2a32-4187-a642-8e32026bfef4",
        "text": "=",
        "metadata": {
            "page": 228,
            "source": "scraped_data/geo.vanderbilt.edu/geo.vanderbilt.edu_part1.txt"
        }
    },
    {
        "id": "d83260dd-dc84-409b-85a6-233f53ce14cc",
        "text": "=",
        "metadata": {
            "page": 229,
            "source": "scraped_data/geo.vanderbilt.edu/geo.vanderbilt.edu_part1.txt"
        }
    },
    {
        "id": "509926eb-a207-46e2-9f15-7c59b3c041f8",
        "text": "=",
        "metadata": {
            "page": 230,
            "source": "scraped_data/geo.vanderbilt.edu/geo.vanderbilt.edu_part1.txt"
        }
    },
    {
        "id": "79ebe3f9-f58f-46e9-bd33-64ab2ee9d0ed",
        "text": "=",
        "metadata": {
            "page": 231,
            "source": "scraped_data/geo.vanderbilt.edu/geo.vanderbilt.edu_part1.txt"
        }
    },
    {
        "id": "0ca49e49-a7ee-46a5-ac42-5f772f582622",
        "text": "=",
        "metadata": {
            "page": 232,
            "source": "scraped_data/geo.vanderbilt.edu/geo.vanderbilt.edu_part1.txt"
        }
    },
    {
        "id": "2487d707-4376-43f3-8ce0-face178ced4c",
        "text": "=",
        "metadata": {
            "page": 233,
            "source": "scraped_data/geo.vanderbilt.edu/geo.vanderbilt.edu_part1.txt"
        }
    },
    {
        "id": "add105bc-0be7-4fab-b0ef-26ceb5261cb6",
        "text": "=",
        "metadata": {
            "page": 234,
            "source": "scraped_data/geo.vanderbilt.edu/geo.vanderbilt.edu_part1.txt"
        }
    },
    {
        "id": "1065f490-df9f-4c4d-914f-774526cd9cb4",
        "text": "=",
        "metadata": {
            "page": 235,
            "source": "scraped_data/geo.vanderbilt.edu/geo.vanderbilt.edu_part1.txt"
        }
    },
    {
        "id": "d52f94f2-7050-458f-991a-cf539d2d873c",
        "text": "=",
        "metadata": {
            "page": 236,
            "source": "scraped_data/geo.vanderbilt.edu/geo.vanderbilt.edu_part1.txt"
        }
    },
    {
        "id": "464593d1-07d7-404f-a9fa-824f2360828e",
        "text": "=",
        "metadata": {
            "page": 237,
            "source": "scraped_data/geo.vanderbilt.edu/geo.vanderbilt.edu_part1.txt"
        }
    },
    {
        "id": "eb5147af-64da-4762-87ce-a4b57e273f63",
        "text": "=",
        "metadata": {
            "page": 238,
            "source": "scraped_data/geo.vanderbilt.edu/geo.vanderbilt.edu_part1.txt"
        }
    },
    {
        "id": "139b3d4a-fcae-4515-b4d0-babc19998dc1",
        "text": "=",
        "metadata": {
            "page": 239,
            "source": "scraped_data/geo.vanderbilt.edu/geo.vanderbilt.edu_part1.txt"
        }
    },
    {
        "id": "32c8a084-652c-4316-bf9e-c049ae6ac1ba",
        "text": "=",
        "metadata": {
            "page": 240,
            "source": "scraped_data/geo.vanderbilt.edu/geo.vanderbilt.edu_part1.txt"
        }
    },
    {
        "id": "bde8b477-baa5-4d04-8185-3add9badcc0a",
        "text": "=",
        "metadata": {
            "page": 241,
            "source": "scraped_data/geo.vanderbilt.edu/geo.vanderbilt.edu_part1.txt"
        }
    },
    {
        "id": "61965420-a88d-46c4-be79-7cd396f92f99",
        "text": "=",
        "metadata": {
            "page": 242,
            "source": "scraped_data/geo.vanderbilt.edu/geo.vanderbilt.edu_part1.txt"
        }
    },
    {
        "id": "a21f0817-5a8c-4c21-a624-a2c73767aa66",
        "text": "=",
        "metadata": {
            "page": 243,
            "source": "scraped_data/geo.vanderbilt.edu/geo.vanderbilt.edu_part1.txt"
        }
    },
    {
        "id": "104c2cc8-f640-459f-9cc9-d5cbc5d98cf9",
        "text": "=",
        "metadata": {
            "page": 244,
            "source": "scraped_data/geo.vanderbilt.edu/geo.vanderbilt.edu_part1.txt"
        }
    },
    {
        "id": "60b540b6-d22f-45c0-a70f-668b7557f580",
        "text": "=",
        "metadata": {
            "page": 245,
            "source": "scraped_data/geo.vanderbilt.edu/geo.vanderbilt.edu_part1.txt"
        }
    },
    {
        "id": "a30e78d0-ef2f-4512-86b5-5968849bcd02",
        "text": "=",
        "metadata": {
            "page": 246,
            "source": "scraped_data/geo.vanderbilt.edu/geo.vanderbilt.edu_part1.txt"
        }
    },
    {
        "id": "92a3ac67-28d1-4449-9489-ad73535fbdb3",
        "text": "=",
        "metadata": {
            "page": 247,
            "source": "scraped_data/geo.vanderbilt.edu/geo.vanderbilt.edu_part1.txt"
        }
    },
    {
        "id": "39d391b8-e493-4972-9662-cd52b1d7bbb7",
        "text": "=",
        "metadata": {
            "page": 248,
            "source": "scraped_data/geo.vanderbilt.edu/geo.vanderbilt.edu_part1.txt"
        }
    },
    {
        "id": "f2da8ca3-c583-4cb5-b83d-47afe7be6ef9",
        "text": "=",
        "metadata": {
            "page": 249,
            "source": "scraped_data/geo.vanderbilt.edu/geo.vanderbilt.edu_part1.txt"
        }
    },
    {
        "id": "ee9a9b2a-2b66-4060-8739-a356dcb44014",
        "text": "=",
        "metadata": {
            "page": 250,
            "source": "scraped_data/geo.vanderbilt.edu/geo.vanderbilt.edu_part1.txt"
        }
    },
    {
        "id": "2ef3ace4-bb6f-4bb2-84f2-74a4ac2893ae",
        "text": "=",
        "metadata": {
            "page": 251,
            "source": "scraped_data/geo.vanderbilt.edu/geo.vanderbilt.edu_part1.txt"
        }
    },
    {
        "id": "97d78786-c0e3-47fc-ba7b-58cb85b9964a",
        "text": "=",
        "metadata": {
            "page": 252,
            "source": "scraped_data/geo.vanderbilt.edu/geo.vanderbilt.edu_part1.txt"
        }
    },
    {
        "id": "f40fbac6-5048-422c-9284-be3e9705d298",
        "text": "=",
        "metadata": {
            "page": 253,
            "source": "scraped_data/geo.vanderbilt.edu/geo.vanderbilt.edu_part1.txt"
        }
    },
    {
        "id": "b6bd49b6-4e8b-4333-942c-c0a8992bae4e",
        "text": "=",
        "metadata": {
            "page": 254,
            "source": "scraped_data/geo.vanderbilt.edu/geo.vanderbilt.edu_part1.txt"
        }
    },
    {
        "id": "c7b26b36-24cd-4170-b05a-84fa5e3c0f63",
        "text": "=",
        "metadata": {
            "page": 255,
            "source": "scraped_data/geo.vanderbilt.edu/geo.vanderbilt.edu_part1.txt"
        }
    },
    {
        "id": "e368b3c1-0fb2-4f64-a14b-ba6daf7cf88e",
        "text": "=",
        "metadata": {
            "page": 256,
            "source": "scraped_data/geo.vanderbilt.edu/geo.vanderbilt.edu_part1.txt"
        }
    },
    {
        "id": "0b895989-77c5-40f2-9bac-397e69d482ee",
        "text": "=",
        "metadata": {
            "page": 257,
            "source": "scraped_data/geo.vanderbilt.edu/geo.vanderbilt.edu_part1.txt"
        }
    },
    {
        "id": "3f83f2e2-1c70-4ee8-aa9b-1d64df8cc0a7",
        "text": "=",
        "metadata": {
            "page": 258,
            "source": "scraped_data/geo.vanderbilt.edu/geo.vanderbilt.edu_part1.txt"
        }
    },
    {
        "id": "49e2dc6f-4cd2-4e8b-8042-f4735cac23f7",
        "text": "=",
        "metadata": {
            "page": 259,
            "source": "scraped_data/geo.vanderbilt.edu/geo.vanderbilt.edu_part1.txt"
        }
    },
    {
        "id": "7bbe70ac-8732-46cb-b144-4b608ff2e625",
        "text": "=",
        "metadata": {
            "page": 260,
            "source": "scraped_data/geo.vanderbilt.edu/geo.vanderbilt.edu_part1.txt"
        }
    },
    {
        "id": "2903d1a5-693a-42fa-8474-124b41c5d27a",
        "text": "=",
        "metadata": {
            "page": 261,
            "source": "scraped_data/geo.vanderbilt.edu/geo.vanderbilt.edu_part1.txt"
        }
    },
    {
        "id": "012a9f9b-228a-4783-b291-2d5c6a18b7c3",
        "text": "=",
        "metadata": {
            "page": 262,
            "source": "scraped_data/geo.vanderbilt.edu/geo.vanderbilt.edu_part1.txt"
        }
    },
    {
        "id": "36d792ee-40da-4979-87b2-7bd087354d7a",
        "text": "=",
        "metadata": {
            "page": 263,
            "source": "scraped_data/geo.vanderbilt.edu/geo.vanderbilt.edu_part1.txt"
        }
    },
    {
        "id": "abd9b688-0d38-4dbd-9cb8-0ed764b728cc",
        "text": "=",
        "metadata": {
            "page": 264,
            "source": "scraped_data/geo.vanderbilt.edu/geo.vanderbilt.edu_part1.txt"
        }
    },
    {
        "id": "aa1af056-d6cd-4a1c-bcf3-3925bcf65e3e",
        "text": "=",
        "metadata": {
            "page": 265,
            "source": "scraped_data/geo.vanderbilt.edu/geo.vanderbilt.edu_part1.txt"
        }
    },
    {
        "id": "e7a08184-e759-43e1-9344-069455d9df34",
        "text": "=",
        "metadata": {
            "page": 266,
            "source": "scraped_data/geo.vanderbilt.edu/geo.vanderbilt.edu_part1.txt"
        }
    },
    {
        "id": "083acf0d-8be5-43e4-8688-f9db114dca4b",
        "text": "=",
        "metadata": {
            "page": 267,
            "source": "scraped_data/geo.vanderbilt.edu/geo.vanderbilt.edu_part1.txt"
        }
    },
    {
        "id": "d3b1b041-ff28-41aa-a082-4c8966f18004",
        "text": "=",
        "metadata": {
            "page": 268,
            "source": "scraped_data/geo.vanderbilt.edu/geo.vanderbilt.edu_part1.txt"
        }
    },
    {
        "id": "9141e1f2-bd45-4ec1-ae0e-ddae003a3472",
        "text": "=",
        "metadata": {
            "page": 269,
            "source": "scraped_data/geo.vanderbilt.edu/geo.vanderbilt.edu_part1.txt"
        }
    },
    {
        "id": "0af96498-de24-4b6d-a3d2-833723a001a0",
        "text": "=",
        "metadata": {
            "page": 270,
            "source": "scraped_data/geo.vanderbilt.edu/geo.vanderbilt.edu_part1.txt"
        }
    },
    {
        "id": "4a574f18-64a9-44df-8da4-51873e9bcc28",
        "text": "=",
        "metadata": {
            "page": 271,
            "source": "scraped_data/geo.vanderbilt.edu/geo.vanderbilt.edu_part1.txt"
        }
    },
    {
        "id": "b232f4b7-97eb-4025-a331-04d37edc8c7c",
        "text": "=",
        "metadata": {
            "page": 272,
            "source": "scraped_data/geo.vanderbilt.edu/geo.vanderbilt.edu_part1.txt"
        }
    },
    {
        "id": "9c013101-3df5-4b8a-a83a-cc31015db150",
        "text": "=",
        "metadata": {
            "page": 273,
            "source": "scraped_data/geo.vanderbilt.edu/geo.vanderbilt.edu_part1.txt"
        }
    },
    {
        "id": "1e13a30c-ed9f-41ad-b550-51248c66cff9",
        "text": "=",
        "metadata": {
            "page": 274,
            "source": "scraped_data/geo.vanderbilt.edu/geo.vanderbilt.edu_part1.txt"
        }
    },
    {
        "id": "392203f9-c512-44d9-85da-3d7b679958d9",
        "text": "=",
        "metadata": {
            "page": 275,
            "source": "scraped_data/geo.vanderbilt.edu/geo.vanderbilt.edu_part1.txt"
        }
    },
    {
        "id": "3d4204c3-ebf3-4530-8be4-fb928ff1faaa",
        "text": "=",
        "metadata": {
            "page": 276,
            "source": "scraped_data/geo.vanderbilt.edu/geo.vanderbilt.edu_part1.txt"
        }
    },
    {
        "id": "d5184b32-050f-4eeb-9a70-ca70155a65ce",
        "text": "=",
        "metadata": {
            "page": 277,
            "source": "scraped_data/geo.vanderbilt.edu/geo.vanderbilt.edu_part1.txt"
        }
    },
    {
        "id": "ca8ded1a-c756-4ee4-8d50-cbc71aedbd63",
        "text": "=",
        "metadata": {
            "page": 278,
            "source": "scraped_data/geo.vanderbilt.edu/geo.vanderbilt.edu_part1.txt"
        }
    },
    {
        "id": "fa63bd67-9a0a-4658-9f71-16f0e5446c9e",
        "text": "=",
        "metadata": {
            "page": 279,
            "source": "scraped_data/geo.vanderbilt.edu/geo.vanderbilt.edu_part1.txt"
        }
    },
    {
        "id": "471f2894-a548-4bac-ba37-0b4fb7713061",
        "text": "=",
        "metadata": {
            "page": 280,
            "source": "scraped_data/geo.vanderbilt.edu/geo.vanderbilt.edu_part1.txt"
        }
    },
    {
        "id": "1b64ce40-8165-44d1-9d9b-638323104ba2",
        "text": "=",
        "metadata": {
            "page": 281,
            "source": "scraped_data/geo.vanderbilt.edu/geo.vanderbilt.edu_part1.txt"
        }
    },
    {
        "id": "b991a342-efe5-4c24-9583-5419510abd93",
        "text": "=",
        "metadata": {
            "page": 282,
            "source": "scraped_data/geo.vanderbilt.edu/geo.vanderbilt.edu_part1.txt"
        }
    },
    {
        "id": "28080c98-3f6d-41c0-8bb5-86763faaabb9",
        "text": "=",
        "metadata": {
            "page": 283,
            "source": "scraped_data/geo.vanderbilt.edu/geo.vanderbilt.edu_part1.txt"
        }
    },
    {
        "id": "b6de5fd1-3a38-40f9-a03f-42961fd2df52",
        "text": "=",
        "metadata": {
            "page": 284,
            "source": "scraped_data/geo.vanderbilt.edu/geo.vanderbilt.edu_part1.txt"
        }
    },
    {
        "id": "adfdf978-4129-4cfd-8f1f-616d95705e14",
        "text": "=",
        "metadata": {
            "page": 285,
            "source": "scraped_data/geo.vanderbilt.edu/geo.vanderbilt.edu_part1.txt"
        }
    },
    {
        "id": "ee23e6e6-d8e9-4df2-8ece-8f5cfcbb2e25",
        "text": "=",
        "metadata": {
            "page": 286,
            "source": "scraped_data/geo.vanderbilt.edu/geo.vanderbilt.edu_part1.txt"
        }
    },
    {
        "id": "5233755e-d7ab-40d7-8ff4-d10aed1f26ef",
        "text": "=",
        "metadata": {
            "page": 287,
            "source": "scraped_data/geo.vanderbilt.edu/geo.vanderbilt.edu_part1.txt"
        }
    },
    {
        "id": "5a6db844-cd36-4469-b9f3-00775cef0097",
        "text": "=",
        "metadata": {
            "page": 288,
            "source": "scraped_data/geo.vanderbilt.edu/geo.vanderbilt.edu_part1.txt"
        }
    },
    {
        "id": "7745e836-cd6f-4669-ab33-86e1fa2cabb4",
        "text": "=",
        "metadata": {
            "page": 289,
            "source": "scraped_data/geo.vanderbilt.edu/geo.vanderbilt.edu_part1.txt"
        }
    },
    {
        "id": "29328a4f-c591-4413-92b9-811f9daecce8",
        "text": "=",
        "metadata": {
            "page": 290,
            "source": "scraped_data/geo.vanderbilt.edu/geo.vanderbilt.edu_part1.txt"
        }
    },
    {
        "id": "cce0f8e8-7edc-4e05-9c65-2282af3f40a8",
        "text": "=",
        "metadata": {
            "page": 291,
            "source": "scraped_data/geo.vanderbilt.edu/geo.vanderbilt.edu_part1.txt"
        }
    },
    {
        "id": "b1293a25-e775-4298-93ed-2bb332dea421",
        "text": "=",
        "metadata": {
            "page": 292,
            "source": "scraped_data/geo.vanderbilt.edu/geo.vanderbilt.edu_part1.txt"
        }
    },
    {
        "id": "0946c739-3596-4c77-9785-632dd669d77a",
        "text": "=",
        "metadata": {
            "page": 293,
            "source": "scraped_data/geo.vanderbilt.edu/geo.vanderbilt.edu_part1.txt"
        }
    },
    {
        "id": "48ed1913-d195-4f61-824b-3c9a369dfd6f",
        "text": "=",
        "metadata": {
            "page": 294,
            "source": "scraped_data/geo.vanderbilt.edu/geo.vanderbilt.edu_part1.txt"
        }
    },
    {
        "id": "ead70cd5-0749-4303-afc6-bfec09baca2b",
        "text": "=",
        "metadata": {
            "page": 295,
            "source": "scraped_data/geo.vanderbilt.edu/geo.vanderbilt.edu_part1.txt"
        }
    },
    {
        "id": "712ec15f-0c29-42b5-a771-84868381d69d",
        "text": "=",
        "metadata": {
            "page": 296,
            "source": "scraped_data/geo.vanderbilt.edu/geo.vanderbilt.edu_part1.txt"
        }
    }
]